tax2graph/GraphParser.py
tax2graph/__init__.py
tax2graph/abstract_connection.py
tax2graph/graph_builder.py
tax2graph/manager.py
tax2graph/data/sordariomycetes/taxa.txt
tax2graph-1.0.3.dist-info/METADATA
tax2graph-1.0.3.dist-info/WHEEL
tax2graph-1.0.3.dist-info/top_level.txt
tax2graph-1.0.3.dist-info/RECORD
