Metadata-Version: 2.1
Name: tax2graph
Version: 1.0.3
Summary: UNKNOWN
Home-page: https://github.com/sgelias/tax2graph.git
Author: Samuel Galvão Elias
Author-email: sgelias@outlook.com
License: UNKNOWN
Keywords: i4Life,Neo4J,Taxonomy
Platform: UNKNOWN
Classifier: Programming Language :: Python :: 3
Classifier: License :: OSI Approved :: MIT License
Classifier: Operating System :: OS Independent
Requires-Python: >=3.6
Requires-Dist: py2neo
Requires-Dist: numpy
Requires-Dist: pandas
